aegon/__init__.py
aegon/libatoms2image.py
aegon/libcalc_emt.py
aegon/libcalc_lj.py
aegon/libcalc_sc.py
aegon/libcalc_tio2.py
aegon/libclusterfactory.py
aegon/libcode.py
aegon/libcode_gaussian.py
aegon/libcode_gulp.py
aegon/libcode_orca.py
aegon/libcode_vasp.py
aegon/libcrossover.py
aegon/libdata_lj.py
aegon/libdata_sc.py
aegon/libdisc_mbtr_clusters.py
aegon/libdisc_mbtr_crystals.py
aegon/libdiscusr.py
aegon/libgcolab.py
aegon/libmolgen.py
aegon/libposcar.py
aegon/libpymatgen.py
aegon/libqueuing.py
aegon/librotamers.py
aegon/libsel_roulette.py
aegon/libstdio.py
aegon/libutils.py
aegon/data/SC_Ag_clusters_data.npz
aegon/data/SC_Al_clusters_data.npz
aegon/data/SC_Au_clusters_data.npz
aegon/data/SC_Cu_clusters_data.npz
aegon/data/SC_Ir_clusters_data.npz
aegon/data/SC_Ni_clusters_data.npz
aegon/data/SC_Pb_clusters_data.npz
aegon/data/SC_Pd_clusters_data.npz
aegon/data/SC_Pt_clusters_data.npz
aegon/data/SC_Rh_clusters_data.npz
aegon/data/libdata_lj.npz
aegon-1.2.5.dist-info/licenses/LICENSE
aegon-1.2.5.dist-info/METADATA
aegon-1.2.5.dist-info/WHEEL
aegon-1.2.5.dist-info/top_level.txt
aegon-1.2.5.dist-info/RECORD
