Metadata-Version: 2.4
Name: aegon
Version: 1.2.5
Summary: Atomic Environment for Global OptimizatioN
Author-email: Filiberto Ortiz Chi <fortiz666@gmail.com>
License: MIT
Project-URL: Homepage, https://github.com/fortizchi/aegon
License-File: LICENSE
Requires-Dist: ase
Requires-Dist: numpy
Requires-Dist: scipy
Requires-Dist: pymatgen
Requires-Dist: py3Dmol
Dynamic: license-file
